agent_gauge/__init__.py
agent_gauge/cost_calculator.py
agent_gauge/logger.py
agent_gauge/monitor.py
agent_gauge/old_monitor.py
agent_gauge/utils.py
agent_gauge/visualizer.py
tests/__init__.py
tests/test_agent_watch.py
agent_gauge-0.0.2.dist-info/LICENSE
agent_gauge-0.0.2.dist-info/METADATA
agent_gauge-0.0.2.dist-info/WHEEL
agent_gauge-0.0.2.dist-info/top_level.txt
agent_gauge-0.0.2.dist-info/RECORD
