Metadata-Version: 2.2
Name: agent_gauge
Version: 0.0.2
Summary: An operational monitoring library for Crew AI applications.
Home-page: https://github.com/shaadclt/Agent-Gauge
Author: Mohamed Shaad
Author-email: shaadclt@gmail.com
Classifier: Programming Language :: Python :: 3
Classifier: License :: OSI Approved :: MIT License
Classifier: Operating System :: OS Independent
Requires-Python: >=3.8
License-File: LICENSE
Requires-Dist: psutil
Requires-Dist: matplotlib
Requires-Dist: streamlit
Requires-Dist: tiktoken
Dynamic: author
Dynamic: author-email
Dynamic: classifier
Dynamic: description
Dynamic: description-content-type
Dynamic: home-page
Dynamic: requires-dist
Dynamic: requires-python
Dynamic: summary
